Workbook

Sheet Start Here
B2: 2026 All-In-One Automated Budget Planner
B3: ✦ Just enter your transactions, everything else calculates automatically ✦
B4: Personal Finance Made Simple — No Excel Knowledge Required
B6: HOW IT WORKS
B7: ① SETUP Open 'Category Setup' Set income & budget targets | C7: ② TRACK Open 'Monthly Tracker' Enter each transaction | D7: ③ REVIEW Open 'Dashboard' See instant analysis | E7: → Repeat Each Month
B10: Open 'Monthly Tracker' sheet. Enter each transaction as it happens. Just type the date, category, and amount.
B11: ✦ WHAT'S INCLUDED
B12: ✔ Auto-Calculations | C12: All totals and balances update instantly as you type.
B13: ✔ Color Coding | C13: Green for income, red for expenses — at a glance clarity.
B14: ✔ 50/30/20 Analysis | C14: Built-in method to split Needs / Wants / Savings automatically.
B15: ✔ Progress Bars | C15: Visual savings goal bars built with spreadsheet formulas.
B16: ✔ Charts & KPIs | C16: Dashboard cards showing income, expenses, balance & savings rate.
B17: ✔ Annual Overview | C17: 12-month bird's-eye view of every income and expense category.
B18: ✔ Debt Tracker | C18: Track balances, interest rates, and months to payoff.
B19: ✔ Savings Goals | C19: 6 preset goals with progress tracking — add your own easily.
B21: PRO TIPS FOR BEST RESULTS
B22: 💡 Update your tracker weekly so no transactions are forgotten.
B23: 💡 Use the same category names consistently for accurate reports.
B24: 💡 Review your Dashboard at the end of each month to spot trends.
B25: 💡 Set realistic budget targets in Category Setup — be honest!
B27: SHEET NAVIGATION
B28: 📋 Category Setup | C28: Set your monthly income & expense budgets
B29: 💳 Monthly Tracker | C29: Log every income & expense transaction
B30: 📊 Dashboard | C30: Visual KPIs, 50/30/20 analysis, budget vs actual
B31: 🎯 Savings Goals | C31: Track progress toward your savings targets
B32: 💸 Debt Tracker | C32: Monitor balances and payoff timelines
B33: 📅 Annual Overview | C33: Full-year income & expense summary
B34: 🗓 Monthly Calendar | C34: Bill due dates and income dates for January 2026
B36: Compatible with Google Sheets & Excel | Digital Download | Personal Use

Sheet Category Setup
B2: CATEGORY SETUP
B3: Set your budget targets below — yellow cells are yours to edit
B5: EXPENSE CATEGORIES
B6: Category | C6: Budget Type (Need/Want/Savings) | D6: Monthly Target ($)
B7: Housing | C7: Need | D7: 2000
B8: Utilities | C8: Need | D8: 180
B9: Groceries | C9: Need | D9: 500
B10: Transportation | C10: Need | D10: 350
B11: Insurance | C11: Need | D11: 250
B12: Healthcare | C12: Need | D12: 150
B13: Dining Out | C13: Want | D13: 200
B14: Entertainment | C14: Want | D14: 100
B15: Shopping | C15: Want | D15: 150
B16: Travel | C16: Want | D16: 100
B17: Hobbies | C17: Want | D17: 80
B18: Subscriptions | C18: Want | D18: 60
... B24: Gifts/Donations | C24: Want | D24: 80
B26: TOTAL BUDGET TARGET | D26: =SUM(D7:D24)
B28: INCOME CATEGORIES
B29: Income Source | C29: Type | D29: Monthly Expected ($)
B30: Salary | C30: Primary | D30: 5500
B31: Side Hustle | C31: Secondary | D31: 500
B32: Investments | C32: Passive | D32: 200
B33: Freelance | C33: Variable | D33: 300
B34: Other | C34: Variable | D34: 100
B36: TOTAL EXPECTED INCOME | D36: =SUM(D30:D34)
B37: PROJECTED MONTHLY SURPLUS | D37: =D36-D26
B39: COLOR LEGEND
B40: ■ | C40: Need — essential expenses (target: ~50% of income)
B41: ■ | C41: Want — lifestyle spending (target: ~30% of income)
B42: ■ | C42: Savings — future & goals (target: ~20% of income)
B43: ■ | C43: Yellow cells = your data to edit

Sheet Monthly Tracker
A1: 6
A2: MONTHLY TRANSACTION TRACKER
A3: Enter each income or expense below — totals calculate automatically
A5: Date | B5: Type (Income/Expense) | C5: Category | D5: Description | E5: Amount ($) | F5: Payment Method | G5: Month | H5: Notes
A6: 2026-01-05 | B6: Income | C6: Salary | D6: January Paycheck | E6: 5500 | F6: Direct Deposit | G6: January
A7: 2026-01-05 | B7: Expense | C7: Housing | D7: Rent — January | E7: 2000 | F7: Bank Transfer | G7: January | H7: Monthly rent
A8: 2026-01-05 | B8: Expense | C8: Insurance | D8: Renters Insurance | E8: 125 | F8: Auto-Pay | G8: January
A9: 2026-01-07 | B9: Expense | C9: Groceries | D9: Whole Foods weekly shop | E9: 127.43 | F9: Debit Card | G9: January
A10: 2026-01-08 | B10: Expense | C10: Utilities | D10: Electric bill | E10: 94.2 | F10: Auto-Pay | G10: January
A11: 2026-01-10 | B11: Expense | C11: Transportation | D11: Subway monthly pass | E11: 132 | F11: Credit Card | G11: January
A12: 2026-01-12 | B12: Expense | C12: Dining Out | D12: Dinner with friends | E12: 68.5 | F12: Credit Card | G12: January
A13: 2026-01-14 | B13: Expense | C13: Subscriptions | D13: Netflix + Spotify | E13: 26.98 | F13: Credit Card | G13: January
A14: 2026-01-15 | B14: Income | C14: Freelance | D14: Website design project | E14: 350 | F14: PayPal | G14: January
A15: 2026-01-16 | B15: Expense | C15: Groceries | D15: Trader Joe's | E15: 89.65 | F15: Debit Card | G15: January
A16: 2026-01-18 | B16: Expense | C16: Entertainment | D16: Movie tickets x2 | E16: 28 | F16: Credit Card | G16: January
A17: 2026-01-20 | B17: Expense | C17: Emergency Fund | D17: Monthly savings transfer | E17: 300 | F17: Bank Transfer | G17: January | H17: Automated
A18: 2026-01-22 | B18: Expense | C18: Healthcare | D18: Prescription refill | E18: 42 | F18: Debit Card | G18: January
A19: 2026-01-25 | B19: Expense | C19: Shopping | D19: Amazon — household items | E19: 56.99 | F19: Credit Card | G19: January
A20: 2026-01-30 | B20: Expense | C20: Debt Payment | D20: Student loan payment | E20: 350 | F20: Auto-Pay | G20: January
A222: TOTAL INCOME | E222: =SUMIF(B6:B220,"Income",E6:E220)
A223: TOTAL EXPENSES | E223: =SUMIF(B6:B220,"Expense",E6:E220)
A224: NET BALANCE (Income − Expenses) | E224: =E222-E223

Sheet Dashboard
B2: FINANCIAL DASHBOARD — 2026
B3: Live summary — updates automatically as you enter transactions
B5: 💰 TOTAL INCOME | C5: 💳 TOTAL EXPENSES | D5: 📊 NET BALANCE | E5: 🎯 SAVINGS RATE
B6: =SUMIF('Monthly Tracker'!B6:B220,"Income",'Monthly Tracker'!E6:E220) | C6: =SUMIF('Monthly Tracker'!B6:B220,"Expense",'Monthly Tracker'!E6:E220) | D6: =SUMIF('Monthly Tracker'!B6:B220,"Income",'Monthly Tracker'!E6:E220)-SUMIF('Monthly Tracker'!B6:B220,"Expense",'Monthly Tracker'!E6:E220) | E6: =IF(SUMIF('Monthly Tracker'!B6:B220,"Income",'Monthly Tracker'!E6:E220)=0,0,(SUMIF('Monthly Tracker'!B6:B220,"Income",'Monthly Tracker'!E6:E220)-SUMIF('Monthly Tracker'!B6:B220,"Expense",'Monthly Tracker'!E6:E220))/SUMIF('Monthly Tracker'!B6:B220,"Income",'Monthly Tracker'!E6:E220))
B10: BUDGET vs ACTUAL — CURRENT MONTH
B11: Category | C11: Budget Target | D11: Actual Spent | E11: Variance | F11: Status
B12: Housing | C12: 2000 | D12: =SUMIFS('Monthly Tracker'!E6:E220,'Monthly Tracker'!B6:B220,"Expense",'Monthly Tracker'!C6:C220,"Housing") | E12: =C12-D12 | F12: =IF(D12<=C12,"✓ Under Budget","✗ Over Budget")
B13: Groceries | C13: 500 | D13: =SUMIFS('Monthly Tracker'!E6:E220,'Monthly Tracker'!B6:B220,"Expense",'Monthly Tracker'!C6:C220,"Groceries") | E13: =C13-D13 | F13: =IF(D13<=C13,"✓ Under Budget","✗ Over Budget")
B14: Transportation | C14: 350 | D14: =SUMIFS('Monthly Tracker'!E6:E220,'Monthly Tracker'!B6:B220,"Expense",'Monthly Tracker'!C6:C220,"Transportation") | E14: =C14-D14 | F14: =IF(D14<=C14,"✓ Under Budget","✗ Over Budget")
B15: Utilities | C15: 180 | D15: =SUMIFS('Monthly Tracker'!E6:E220,'Monthly Tracker'!B6:B220,"Expense",'Monthly Tracker'!C6:C220,"Utilities") | E15: =C15-D15 | F15: =IF(D15<=C15,"✓ Under Budget","✗ Over Budget")
B16: Dining Out | C16: 200 | D16: =SUMIFS('Monthly Tracker'!E6:E220,'Monthly Tracker'!B6:B220,"Expense",'Monthly Tracker'!C6:C220,"Dining Out") | E16: =C16-D16 | F16: =IF(D16<=C16,"✓ Under Budget","✗ Over Budget")
B17: Entertainment | C17: 100 | D17: =SUMIFS('Monthly Tracker'!E6:E220,'Monthly Tracker'!B6:B220,"Expense",'Monthly Tracker'!C6:C220,"Entertainment") | E17: =C17-D17 | F17: =IF(D17<=C17,"✓ Under Budget","✗ Over Budget")
B18: Shopping | C18: 150 | D18: =SUMIFS('Monthly Tracker'!E6:E220,'Monthly Tracker'!B6:B220,"Expense",'Monthly Tracker'!C6:C220,"Shopping") | E18: =C18-D18 | F18: =IF(D18<=C18,"✓ Under Budget","✗ Over Budget")
B19: Emergency Fund | C19: 300 | D19: =SUMIFS('Monthly Tracker'!E6:E220,'Monthly Tracker'!B6:B220,"Expense",'Monthly Tracker'!C6:C220,"Emergency Fund") | E19: =C19-D19 | F19: =IF(D19<=C19,"✓ Under Budget","✗ Over Budget")
B20: Debt Payment | C20: 500 | D20: =SUMIFS('Monthly Tracker'!E6:E220,'Monthly Tracker'!B6:B220,"Expense",'Monthly Tracker'!C6:C220,"Debt Payment") | E20: =C20-D20 | F20: =IF(D20<=C20,"✓ Under Budget","✗ Over Budget")
B21: Healthcare | C21: 150 | D21: =SUMIFS('Monthly Tracker'!E6:E220,'Monthly Tracker'!B6:B220,"Expense",'Monthly Tracker'!C6:C220,"Healthcare") | E21: =C21-D21 | F21: =IF(D21<=C21,"✓ Under Budget","✗ Over Budget")
B23: 50/30/20 BUDGET ANALYSIS
B24: Category | C24: Target % | D24: Target Amount | E24: Actual Amount | F24: Status
B25: Needs (50%) | C25: 0.5 | D25: =SUMIF('Monthly Tracker'!B6:B220,"Income",'Monthly Tracker'!E6:E220)*0.5 | E25: =SUMIFS('Monthly Tracker'!E6:E220,'Monthly Tracker'!B6:B220,"Expense",'Monthly Tracker'!C6:C220,"Housing")+SUMIFS('Monthly Tracker'!E6:E220,'Monthly Tracker'!B6:B220,"Expense",'Monthly Tracker'!C6:C220,"Utilities")+SUMIFS('Monthly Tracker'!E6:E220,'Monthly Tracker'!B6:B220,"Expense",'Monthly Tracker'!C6:C220,"Groceries")+SUMIFS('Monthly Tracker'!E6:E220,'Monthly Tracker'!B6:B220,"Expense",'Monthly Tracker'!C6:C220,"Transportation")+SUMIFS('Monthly Tracker'!E6:E220,'Monthly Tracker'!B6:B220,"Expense",'Monthly Tracker'!C6:C220,"Insurance")+SUMIFS('Monthly Tracker'!E6:E220,'Monthly Tracker'!B6:B220,"Expense",'Monthly Tracker'!C6:C220,"Healthcare")+SUMIFS('Monthly Tracker'!E6:E220,'Monthly Tracker'!B6:B220,"Expense",'Monthly Tracker'!C6:C220,"Debt Payment") | F25: =IF(E25<=D25,"✓ On Track","⚠ Adjust")
B26: Wants (30%) | C26: 0.3 | D26: =SUMIF('Monthly Tracker'!B6:B220,"Income",'Monthly Tracker'!E6:E220)*0.3 | E26: =SUMIFS('Monthly Tracker'!E6:E220,'Monthly Tracker'!B6:B220,"Expense",'Monthly Tracker'!C6:C220,"Dining Out")+SUMIFS('Monthly Tracker'!E6:E220,'Monthly Tracker'!B6:B220,"Expense",'Monthly Tracker'!C6:C220,"Entertainment")+SUMIFS('Monthly Tracker'!E6:E220,'Monthly Tracker'!B6:B220,"Expense",'Monthly Tracker'!C6:C220,"Shopping")+SUMIFS('Monthly Tracker'!E6:E220,'Monthly Tracker'!B6:B220,"Expense",'Monthly Tracker'!C6:C220,"Travel")+SUMIFS('Monthly Tracker'!E6:E220,'Monthly Tracker'!B6:B220,"Expense",'Monthly Tracker'!C6:C220,"Hobbies")+SUMIFS('Monthly Tracker'!E6:E220,'Monthly Tracker'!B6:B220,"Expense",'Monthly Tracker'!C6:C220,"Subscriptions")+SUMIFS('Monthly Tracker'!E6:E220,'Monthly Tracker'!B6:B220,"Expense",'Monthly Tracker'!C6:C220,"Education")+SUMIFS('Monthly Tracker'!E6:E220,'Monthly Tracker'!B6:B220,"Expense",'Monthly Tracker'!C6:C220,"Gifts/Donations") | F26: =IF(E26<=D26,"✓ On Track","⚠ Adjust")
B27: Savings (20%) | C27: 0.2 | D27: =SUMIF('Monthly Tracker'!B6:B220,"Income",'Monthly Tracker'!E6:E220)*0.2 | E27: =SUMIFS('Monthly Tracker'!E6:E220,'Monthly Tracker'!B6:B220,"Expense",'Monthly Tracker'!C6:C220,"Emergency Fund")+SUMIFS('Monthly Tracker'!E6:E220,'Monthly Tracker'!B6:B220,"Expense",'Monthly Tracker'!C6:C220,"Retirement")+SUMIFS('Monthly Tracker'!E6:E220,'Monthly Tracker'!B6:B220,"Expense",'Monthly Tracker'!C6:C220,"Investments") | F27: =IF(E27<=D27,"✓ On Track","⚠ Adjust")
B29: 💡 Tip: Add transactions to 'Monthly Tracker' and this dashboard updates automatically!

Sheet Savings Goals
B2: SAVINGS GOALS TRACKER
B3: Track progress toward your financial goals — yellow cells are yours to edit
B5: Goal Name | C5: Target Amount | D5: Current Saved | E5: Remaining | F5: Progress % | G5: Visual Progress ████░░░░
B6: 🚨 Emergency Fund | C6: 10000 | D6: 3200 | E6: =C6-D6 | F6: =IF(C6=0,0,D6/C6) | G6: =IFERROR(REPT("█",ROUND(F6*20,0))&REPT("░",20-ROUND(F6*20,0)),"░░░░░░░░░░░░░░░░░░░░")
B7: ✈️ Vacation Fund | C7: 3000 | D7: 1750 | E7: =C7-D7 | F7: =IF(C7=0,0,D7/C7) | G7: =IFERROR(REPT("█",ROUND(F7*20,0))&REPT("░",20-ROUND(F7*20,0)),"░░░░░░░░░░░░░░░░░░░░")
B8: 🚗 New Car | C8: 15000 | D8: 4500 | E8: =C8-D8 | F8: =IF(C8=0,0,D8/C8) | G8: =IFERROR(REPT("█",ROUND(F8*20,0))&REPT("░",20-ROUND(F8*20,0)),"░░░░░░░░░░░░░░░░░░░░")
B9: 🏠 Home Down Payment | C9: 50000 | D9: 8000 | E9: =C9-D9 | F9: =IF(C9=0,0,D9/C9) | G9: =IFERROR(REPT("█",ROUND(F9*20,0))&REPT("░",20-ROUND(F9*20,0)),"░░░░░░░░░░░░░░░░░░░░")
B10: 💍 Wedding | C10: 20000 | D10: 6500 | E10: =C10-D10 | F10: =IF(C10=0,0,D10/C10) | G10: =IFERROR(REPT("█",ROUND(F10*20,0))&REPT("░",20-ROUND(F10*20,0)),"░░░░░░░░░░░░░░░░░░░░")
B11: 📚 Education Fund | C11: 8000 | D11: 2400 | E11: =C11-D11 | F11: =IF(C11=0,0,D11/C11) | G11: =IFERROR(REPT("█",ROUND(F11*20,0))&REPT("░",20-ROUND(F11*20,0)),"░░░░░░░░░░░░░░░░░░░░")
B13: ADD YOUR OWN GOALS BELOW
E14: =IF(C14=0,"",C14-D14) | F14: =IF(C14=0,"",IF(D14=0,0,D14/C14)) | G14: =IF(C14=0,"",IFERROR(REPT("█",ROUND(F14*20,0))&REPT("░",20-ROUND(F14*20,0)),""))
E15: =IF(C15=0,"",C15-D15) | F15: =IF(C15=0,"",IF(D15=0,0,D15/C15)) | G15: =IF(C15=0,"",IFERROR(REPT("█",ROUND(F15*20,0))&REPT("░",20-ROUND(F15*20,0)),""))
E16: =IF(C16=0,"",C16-D16) | F16: =IF(C16=0,"",IF(D16=0,0,D16/C16)) | G16: =IF(C16=0,"",IFERROR(REPT("█",ROUND(F16*20,0))&REPT("░",20-ROUND(F16*20,0)),""))
E17: =IF(C17=0,"",C17-D17) | F17: =IF(C17=0,"",IF(D17=0,0,D17/C17)) | G17: =IF(C17=0,"",IFERROR(REPT("█",ROUND(F17*20,0))&REPT("░",20-ROUND(F17*20,0)),""))
E18: =IF(C18=0,"",C18-D18) | F18: =IF(C18=0,"",IF(D18=0,0,D18/C18)) | G18: =IF(C18=0,"",IFERROR(REPT("█",ROUND(F18*20,0))&REPT("░",20-ROUND(F18*20,0)),""))
E19: =IF(C19=0,"",C19-D19) | F19: =IF(C19=0,"",IF(D19=0,0,D19/C19)) | G19: =IF(C19=0,"",IFERROR(REPT("█",ROUND(F19*20,0))&REPT("░",20-ROUND(F19*20,0)),""))
E20: =IF(C20=0,"",C20-D20) | F20: =IF(C20=0,"",IF(D20=0,0,D20/C20)) | G20: =IF(C20=0,"",IFERROR(REPT("█",ROUND(F20*20,0))&REPT("░",20-ROUND(F20*20,0)),""))
E21: =IF(C21=0,"",C21-D21) | F21: =IF(C21=0,"",IF(D21=0,0,D21/C21)) | G21: =IF(C21=0,"",IFERROR(REPT("█",ROUND(F21*20,0))&REPT("░",20-ROUND(F21*20,0)),""))
B23: TOTALS SUMMARY
B24: Total Goal Amount | G24: =SUM(C6:C11)
B25: Total Saved | G25: =SUM(D6:D11)
B26: Total Remaining | G26: =SUM(E6:E11)

Sheet Debt Tracker
B2: DEBT PAYOFF TRACKER
B3: Monitor your debt balances and see your payoff timeline at a glance
B5: Debt Name | C5: Original Balance | D5: Interest Rate % | E5: Min Payment | F5: Extra Payment | G5: Current Balance | H5: Months to Payoff | I5: Progress %
B6: 🎓 Student Loan | C6: 25000 | D6: 0.045 | E6: 285 | F6: 100 | G6: 22500 | H6: =IF((E6+F6)=0,"N/A",ROUND(G6/(E6+F6),0)) | I6: =IF(C6=0,0,1-(G6/C6))
B7: 💳 Credit Card | C7: 3500 | D7: 0.199 | E7: 70 | F7: 150 | G7: 3200 | H7: =IF((E7+F7)=0,"N/A",ROUND(G7/(E7+F7),0)) | I7: =IF(C7=0,0,1-(G7/C7))
B8: 🚗 Car Loan | C8: 18000 | D8: 0.035 | E8: 320 | F8: 50 | G8: 14800 | H8: =IF((E8+F8)=0,"N/A",ROUND(G8/(E8+F8),0)) | I8: =IF(C8=0,0,1-(G8/C8))
B9: 💼 Personal Loan | C9: 8000 | D9: 0.089 | E9: 180 | F9: 75 | G9: 6500 | H9: =IF((E9+F9)=0,"N/A",ROUND(G9/(E9+F9),0)) | I9: =IF(C9=0,0,1-(G9/C9))
B11: TOTALS | C11: =SUM(C6:C9) | E11: =SUM(E6:E9) | F11: =SUM(F6:F9) | G11: =SUM(G6:G9)
B13: TIPS & STRATEGIES
B14: 💡 PAYOFF STRATEGY TIP: | C14: Pay minimums on all debts, then put every extra dollar on the highest-interest debt first (Avalanche Method).
B15: 📅 MONTHLY REVIEW: | C15: Update 'Current Balance' each month after payments to track your progress accurately.
B16: 🎯 EXTRA PAYMENTS: | C16: Even $50 extra per month can save hundreds in interest and months of payments.

Sheet Annual Overview
A2: ANNUAL FINANCIAL OVERVIEW — 2026
B4: Category | C4: Jan | D4: Feb | E4: Mar | F4: Apr | G4: May | H4: Jun | I4: Jul | J4: Aug | K4: Sep | L4: Oct | M4: Nov | N4: Dec | O4: Full Year Total | P4: Monthly Avg
A5: ▶ INCOME
B6: Salary | O6: =SUM(C6:N6) | P6: =IF(O6=0,0,O6/12)
B7: Side Hustle | O7: =SUM(C7:N7) | P7: =IF(O7=0,0,O7/12)
B8: Investments | O8: =SUM(C8:N8) | P8: =IF(O8=0,0,O8/12)
B9: Freelance | O9: =SUM(C9:N9) | P9: =IF(O9=0,0,O9/12)
B10: Other | O10: =SUM(C10:N10) | P10: =IF(O10=0,0,O10/12)
B11: TOTAL INCOME | C11: =C6+C7+C8+C9+C10 | D11: =D6+D7+D8+D9+D10 | E11: =E6+E7+E8+E9+E10 | F11: =F6+F7+F8+F9+F10 | G11: =G6+G7+G8+G9+G10 | H11: =H6+H7+H8+H9+H10 | I11: =I6+I7+I8+I9+I10 | J11: =J6+J7+J8+J9+J10 | ... N11: =N6+N7+N8+N9+N10 | O11: =SUM(C11:N11) | P11: =O11/12
A13: ▶ EXPENSES
B14: Housing | O14: =SUM(C14:N14) | P14: =IF(O14=0,0,O14/12)
B15: Utilities | O15: =SUM(C15:N15) | P15: =IF(O15=0,0,O15/12)
B16: Groceries | O16: =SUM(C16:N16) | P16: =IF(O16=0,0,O16/12)
B17: Transportation | O17: =SUM(C17:N17) | P17: =IF(O17=0,0,O17/12)
B18: Insurance | O18: =SUM(C18:N18) | P18: =IF(O18=0,0,O18/12)
B19: Healthcare | O19: =SUM(C19:N19) | P19: =IF(O19=0,0,O19/12)
B20: Dining Out | O20: =SUM(C20:N20) | P20: =IF(O20=0,0,O20/12)
B21: Entertainment | O21: =SUM(C21:N21) | P21: =IF(O21=0,0,O21/12)
B22: Shopping | O22: =SUM(C22:N22) | P22: =IF(O22=0,0,O22/12)
B23: Subscriptions | O23: =SUM(C23:N23) | P23: =IF(O23=0,0,O23/12)
B24: Savings / Emergency | O24: =SUM(C24:N24) | P24: =IF(O24=0,0,O24/12)
B25: Debt Payment | O25: =SUM(C25:N25) | P25: =IF(O25=0,0,O25/12)
... B27: Other | O27: =SUM(C27:N27) | P27: =IF(O27=0,0,O27/12)
B28: TOTAL EXPENSES | C28: =C14+C15+C16+C17+C18+C19+C20+C21+C22+C23+C24+C25+C26+C27 | D28: =D14+D15+D16+D17+D18+D19+D20+D21+D22+D23+D24+D25+D26+D27 | E28: =E14+E15+E16+E17+E18+E19+E20+E21+E22+E23+E24+E25+E26+E27 | F28: =F14+F15+F16+F17+F18+F19+F20+F21+F22+F23+F24+F25+F26+F27 | G28: =G14+G15+G16+G17+G18+G19+G20+G21+G22+G23+G24+G25+G26+G27 | H28: =H14+H15+H16+H17+H18+H19+H20+H21+H22+H23+H24+H25+H26+H27 | I28: =I14+I15+I16+I17+I18+I19+I20+I21+I22+I23+I24+I25+I26+I27 | J28: =J14+J15+J16+J17+J18+J19+J20+J21+J22+J23+J24+J25+J26+J27 | ... N28: =N14+N15+N16+N17+N18+N19+N20+N21+N22+N23+N24+N25+N26+N27 | O28: =SUM(C28:N28) | P28: =O28/12
B30: NET SURPLUS / DEFICIT | C30: =C11-C28 | D30: =D11-D28 | E30: =E11-E28 | F30: =F11-F28 | G30: =G11-G28 | H30: =H11-H28 | I30: =I11-I28 | J30: =J11-J28 | ... O30: =O11-O28 | P30: =O30/12

Sheet Monthly Calendar
B2: JANUARY 2026 — BILL PAYMENT CALENDAR
B3: Red = Bill Due | Green = Income Day | Gray = Regular Day
B4: Monday | C4: Tuesday | D4: Wednesday | E4: Thursday | F4: Friday | G4: Saturday | H4: Sunday
E5: 1 | F5: 2 | G5: 3 | H5: 4
B6: 5 📋 Rent 💰 Salary | C6: 6 | D6: 7 | E6: 8 📋 Electric | F6: 9 | G6: 10 | H6: 11
B7: 12 | C7: 13 | D7: 14 | E7: 15 💰 Freelance | F7: 16 📋 Netflix | G7: 17 | H7: 18
B8: 19 | C8: 20 📋 Savings Xfer | D8: 21 | E8: 22 | F8: 23 | G8: 24 | H8: 25
B9: 26 | C9: 27 | D9: 28 | E9: 29 | F9: 30 📋 Student Loan | G9: 31
B11: JANUARY 2026 — UPCOMING BILLS & PAYMENTS
B12: Date | C12: Bill / Item | E12: Amount | G12: Auto-Pay? | H12: Status
B13: Jan 5 | C13: 🏠 Rent | E13: 2000 | G13: Yes | H13: Paid
B14: Jan 8 | C14: ⚡ Electric Bill | E14: 94.2 | G14: Yes | H14: Paid
B15: Jan 15 | C15: 💰 Freelance Income | E15: 350 | G15: — | H15: Received
B16: Jan 16 | C16: 📺 Netflix + Spotify | E16: 26.98 | G16: Yes | H16: Upcoming
B17: Jan 20 | C17: 🏦 Savings Transfer | E17: 300 | G17: Yes | H17: Upcoming
B18: Jan 30 | C18: 🎓 Student Loan | E18: 350 | G18: Yes | H18: Upcoming
B20: LEGEND
B21: 📋 Red Background = Bill Due Date
B22: 💰 Green Background = Income / Payday
B23: ⬜ Gray Background = Regular Day
